README.txt
setup.py
collective/__init__.py
collective.datehacker.egg-info/PKG-INFO
collective.datehacker.egg-info/SOURCES.txt
collective.datehacker.egg-info/dependency_links.txt
collective.datehacker.egg-info/entry_points.txt
collective.datehacker.egg-info/namespace_packages.txt
collective.datehacker.egg-info/not-zip-safe
collective.datehacker.egg-info/paster_plugins.txt
collective.datehacker.egg-info/requires.txt
collective.datehacker.egg-info/top_level.txt
collective/datehacker/__init__.py
collective/datehacker/configure.zcml
collective/datehacker/tests.py
collective/datehacker/browser/__init__.py
collective/datehacker/browser/configure.zcml
collective/datehacker/browser/hack_dates.pt
collective/datehacker/browser/hackdate.py
collective/datehacker/locales/collective.datehacker.pot
collective/datehacker/locales/i18n.sh
collective/datehacker/locales/it/LC_MESSAGES/collective.datehacker.mo
collective/datehacker/locales/it/LC_MESSAGES/collective.datehacker.po
docs/HISTORY.txt
docs/INSTALL.txt
docs/LICENSE.GPL
docs/LICENSE.txt