Metadata-Version: 1.0
Name: collective.datehacker
Version: 0.1.0a
Summary: Add to Plone a view for changing (cheating!) creation and last modification date
Home-page: http://svn.plone.org/svn/collective/collective.datehacker
Author: RedTurtle Technology
Author-email: sviluppoplone@redturtle.net
License: GPL
Keywords: plone plonegov date creation-date modification-date
Platform: UNKNOWN
Classifier: Framework :: Plone
Classifier: Programming Language :: Python
Classifier: Development Status :: 3 - Alpha
